data/configuration.schema
dice_maiden_ui/__main__.py
dice_maiden_ui/configuration.py
dice_maiden_ui/gui.py
dice_maiden_ui/models.py
dice_maiden_ui/roll.py
dice_maiden_ui-1.0.0.dist-info/entry_points.txt
dice_maiden_ui-1.0.0.dist-info/LICENSE.md
dice_maiden_ui-1.0.0.dist-info/WHEEL
dice_maiden_ui-1.0.0.dist-info/METADATA
dice_maiden_ui-1.0.0.dist-info/RECORD
