Metadata-Version: 2.1
Name: dice-maiden-ui
Version: 1.0.0
Summary: GUI application designed to generate dice maiden roll commands
Home-page: https://github.com/jjmar/dice-maiden-ui
License: GPL-3.0-only
Author: Justin Martin
Author-email: jjmardev@gmail.com
Requires-Python: >=3.6,<4.0
Classifier: License :: OSI Approved :: GNU General Public License v3 (GPLv3)
Classifier: Programming Language :: Python :: 3
Classifier: Programming Language :: Python :: 3.6
Classifier: Programming Language :: Python :: 3.7
Classifier: Programming Language :: Python :: 3.8
Classifier: Programming Language :: Python :: 3.9
Requires-Dist: jsonschema (>=3.2.0,<4.0.0)
Requires-Dist: pyperclip (>=1.8.2,<2.0.0)
Project-URL: Repository, https://github.com/jjmar/dice-maiden-ui
